config_decorator/__init__.py
config_decorator/config_decorator.py
config_decorator/key_chained_val.py
config_decorator/slug_name_util.py
config_decorator-2.0.18.dist-info/LICENSE
config_decorator-2.0.18.dist-info/METADATA
config_decorator-2.0.18.dist-info/WHEEL
config_decorator-2.0.18.dist-info/RECORD
